.gitignore
COPYING
DESCRIPTION.rst
README.md
blackstar-id.rules
outsider-screenshot.png
setup.py
blackstarid/__init__.py
blackstarid/blackstarid.py
outsider/__init__.py
outsider/__main__.py
outsider/outsider.py
outsider/outsider.ui
outsider/version.py
outsider.egg-info/PKG-INFO
outsider.egg-info/SOURCES.txt
outsider.egg-info/dependency_links.txt
outsider.egg-info/entry_points.txt
outsider.egg-info/requires.txt
outsider.egg-info/top_level.txt